MANIFEST.in
README.rst
requirements.txt
setup.cfg
setup.py
eceibs/__init__.py
eceibs.egg-info/PKG-INFO
eceibs.egg-info/SOURCES.txt
eceibs.egg-info/dependency_links.txt
eceibs.egg-info/not-zip-safe
eceibs.egg-info/requires.txt
eceibs.egg-info/top_level.txt
eceibs/client/__init__.py
eceibs/client/base.py
eceibs/client/api/__init__.py
eceibs/client/api/auth.py
eceibs/client/api/base.py
eceibs/client/api/column.py
eceibs/client/api/open.py
eceibs/core/__init__.py
eceibs/core/exceptions.py
eceibs/core/utils.py
eceibs/storage/__init__.py
eceibs/storage/cache.py
eceibs/storage/kvstorage.py
eceibs/storage/memorystorage.py