Metadata-Version: 1.1
Name: eceibs
Version: 1.0.2
Summary: eceibs SDK for Python
Home-page: https://github.com/007gzs/eceibs
Author: 007gzs
Author-email: 007gzs@sina.com
License: LGPL v3
Keywords: eceibs,SDK
Platform: UNKNOWN
Classifier: Development Status :: 3 - Alpha
Classifier: Intended Audience :: Developers
Classifier: Topic :: Software Development :: Build Tools
Classifier: License :: OSI Approved :: GNU Lesser General Public License v3 (LGPLv3)
Classifier: Programming Language :: Python :: 3
Classifier: Programming Language :: Python :: 3.4
Classifier: Programming Language :: Python :: 3.5
Classifier: Programming Language :: Python :: 3.6
Classifier: Programming Language :: Python :: 3.7
